{
  "book": "A Christmas Carol",
  "num_sections": 5,
  "sections": [{
    "names": ["Jacob Marley", "Ebenezer Scrooge", "Pharaoh", "Prophet"],
    "matrix": [
      [0.0, 0.83333, 0.08333, 0.08333],
      [1.0, 0.0, 0.0, 0.0],
      [0.5, 0.0, 0.0, 0.5],
      [0.5, 0.0, 0.5, 0.0]
    ]
  }, {
    "names": ["Ebenezer Scrooge", "Jacob Marley", "Pharaoh", "Prophet", "Orson", "Valentine", "Dick Wilkins"],
    "matrix": [
      [0.0, 0.76923, 0.0, 0.0, 0.07692, 0.07692, 0.07692],
      [0.83333, 0.0, 0.08333, 0.08333, 0.0, 0.0, 0.0],
      [0.0, 0.5, 0.0, 0.5, 0.0, 0.0, 0.0],
      [0.0, 0.5, 0.5, 0.0, 0.0, 0.0, 0.0],
      [0.5, 0.0, 0.0, 0.0, 0.0, 0.5, 0.0],
      [0.5, 0.0, 0.0, 0.0, 0.5, 0.0, 0.0],
      [1.0, 0.0, 0.0, 0.0, 0.0, 0.0, 0.0]
    ]
  }, {
    "names": ["Ebenezer Scrooge", "Belinda Cratchit", "Bob Cratchit", "Tiny Tim", "Jacob Marley", "Peter Cratchit", "Pharaoh", "Prophet", "Orson", "Valentine", "Martha", "Parks", "Fred", "Hurrah", "Dick Wilkins"],
    "matrix": [
      [0.0, 0.0, 0.09524, 0.09524, 0.52381, 0.0, 0.0, 0.0, 0.04762, 0.04762, 0.0, 0.0, 0.14286, 0.0, 0.04762],
      [0.0, 0.0, 0.35, 0.2, 0.0, 0.2, 0.0, 0.0, 0.0, 0.0, 0.1, 0.1, 0.0, 0.05, 0.0],
      [0.08696, 0.30435, 0.0, 0.26087, 0.0, 0.17391, 0.0, 0.0, 0.0, 0.0, 0.13043, 0.04348, 0.0, 0.0, 0.0],
      [0.11111, 0.22222, 0.33333, 0.0, 0.0, 0.11111, 0.0, 0.0, 0.0, 0.0, 0.16667, 0.0, 0.0, 0.05556, 0.0],
      [0.84615, 0.0, 0.0, 0.0, 0.0, 0.0, 0.07692, 0.07692, 0.0, 0.0, 0.0, 0.0, 0.0, 0.0, 0.0],
      [0.0, 0.33333, 0.33333, 0.16667, 0.0, 0.0, 0.0, 0.0, 0.0, 0.0, 0.08333, 0.08333, 0.0, 0.0, 0.0],
      [0.0, 0.0, 0.0, 0.0, 0.5, 0.0, 0.0, 0.5, 0.0, 0.0, 0.0, 0.0, 0.0, 0.0, 0.0],
      [0.0, 0.0, 0.0, 0.0, 0.5, 0.0, 0.5, 0.0, 0.0, 0.0, 0.0, 0.0, 0.0, 0.0, 0.0],
      [0.5, 0.0, 0.0, 0.0, 0.0, 0.0, 0.0, 0.0, 0.0, 0.5, 0.0, 0.0, 0.0, 0.0, 0.0],
      [0.5, 0.0, 0.0, 0.0, 0.0, 0.0, 0.0, 0.0, 0.5, 0.0, 0.0, 0.0, 0.0, 0.0, 0.0],
      [0.0, 0.22222, 0.33333, 0.33333, 0.0, 0.11111, 0.0, 0.0, 0.0, 0.0, 0.0, 0.0, 0.0, 0.0, 0.0],
      [0.0, 0.5, 0.25, 0.0, 0.0, 0.25, 0.0, 0.0, 0.0, 0.0, 0.0, 0.0, 0.0, 0.0, 0.0],
      [1.0, 0.0, 0.0, 0.0, 0.0, 0.0, 0.0, 0.0, 0.0, 0.0, 0.0, 0.0, 0.0, 0.0, 0.0],
      [0.0, 0.5, 0.0, 0.5, 0.0, 0.0, 0.0, 0.0, 0.0, 0.0, 0.0, 0.0, 0.0, 0.0, 0.0],
      [1.0, 0.0, 0.0, 0.0, 0.0, 0.0, 0.0, 0.0, 0.0, 0.0, 0.0, 0.0, 0.0, 0.0, 0.0]
    ]
  }, {
    "names": ["Ebenezer Scrooge", "Belinda Cratchit", "Bob Cratchit", "Tiny Tim", "Jacob Marley", "Peter Cratchit", "Pharaoh", "Prophet", "Orson", "Valentine", "Martha", "Parks", "Fred", "Hurrah", "Dick Wilkins", "Joe Miller"],
    "matrix": [
      [0.0, 0.0, 0.13636, 0.09091, 0.5, 0.0, 0.0, 0.0, 0.04545, 0.04545, 0.0, 0.0, 0.13636, 0.0, 0.04545, 0.0],
      [0.0, 0.0, 0.31818, 0.18182, 0.0, 0.27273, 0.0, 0.0, 0.0, 0.0, 0.09091, 0.09091, 0.0, 0.04545, 0.0, 0.0],
      [0.12, 0.28, 0.0, 0.28, 0.0, 0.16, 0.0, 0.0, 0.0, 0.0, 0.12, 0.04, 0.0, 0.0, 0.0, 0.0],
      [0.10526, 0.21053, 0.36842, 0.0, 0.0, 0.10526, 0.0, 0.0, 0.0, 0.0, 0.15789, 0.0, 0.0, 0.05263, 0.0, 0.0],
      [0.84615, 0.0, 0.0, 0.0, 0.0, 0.0, 0.07692, 0.07692, 0.0, 0.0, 0.0, 0.0, 0.0, 0.0, 0.0, 0.0],
      [0.0, 0.42857, 0.28571, 0.14286, 0.0, 0.0, 0.0, 0.0, 0.0, 0.0, 0.07143, 0.07143, 0.0, 0.0, 0.0, 0.0],
      [0.0, 0.0, 0.0, 0.0, 0.5, 0.0, 0.0, 0.5, 0.0, 0.0, 0.0, 0.0, 0.0, 0.0, 0.0, 0.0],
      [0.0, 0.0, 0.0, 0.0, 0.5, 0.0, 0.5, 0.0, 0.0, 0.0, 0.0, 0.0, 0.0, 0.0, 0.0, 0.0],
      [0.5, 0.0, 0.0, 0.0, 0.0, 0.0, 0.0, 0.0, 0.0, 0.5, 0.0, 0.0, 0.0, 0.0, 0.0, 0.0],
      [0.5, 0.0, 0.0, 0.0, 0.0, 0.0, 0.0, 0.0, 0.5, 0.0, 0.0, 0.0, 0.0, 0.0, 0.0, 0.0],
      [0.0, 0.22222, 0.33333, 0.33333, 0.0, 0.11111, 0.0, 0.0, 0.0, 0.0, 0.0, 0.0, 0.0, 0.0, 0.0, 0.0],
      [0.0, 0.5, 0.25, 0.0, 0.0, 0.25, 0.0, 0.0, 0.0, 0.0, 0.0, 0.0, 0.0, 0.0, 0.0, 0.0],
      [1.0, 0.0, 0.0, 0.0, 0.0, 0.0, 0.0, 0.0, 0.0, 0.0, 0.0, 0.0, 0.0, 0.0, 0.0, 0.0],
      [0.0, 0.5, 0.0, 0.5, 0.0, 0.0, 0.0, 0.0, 0.0, 0.0, 0.0, 0.0, 0.0, 0.0, 0.0, 0.0],
      [1.0, 0.0, 0.0, 0.0, 0.0, 0.0, 0.0, 0.0, 0.0, 0.0, 0.0, 0.0, 0.0, 0.0, 0.0, 0.0],
      [0.0, 0.0, 0.0, 0.0, 0.0, 0.0, 0.0, 0.0, 0.0, 0.0, 0.0, 0.0, 0.0, 0.0, 0.0, 0.0]
    ]
  }, {
    "names": ["Ebenezer Scrooge", "Bob Cratchit", "Belinda Cratchit", "Tiny Tim", "Jacob Marley", "Peter Cratchit", "Pharaoh", "Prophet", "Orson", "Valentine", "Martha", "Parks", "Fred", "Hurrah", "Dick Wilkins", "Joe Miller"],
    "matrix": [
      [0.0, 0.2, 0.0, 0.08, 0.48, 0.0, 0.0, 0.0, 0.04, 0.04, 0.0, 0.0, 0.12, 0.0, 0.04, 0.0],
      [0.17857, 0.0, 0.25, 0.25, 0.0, 0.14286, 0.0, 0.0, 0.0, 0.0, 0.10714, 0.03571, 0.0, 0.0, 0.0, 0.03571],
      [0.0, 0.31818, 0.0, 0.18182, 0.0, 0.27273, 0.0, 0.0, 0.0, 0.0, 0.09091, 0.09091, 0.0, 0.04545, 0.0, 0.0],
      [0.10526, 0.36842, 0.21053, 0.0, 0.0, 0.10526, 0.0, 0.0, 0.0, 0.0, 0.15789, 0.0, 0.0, 0.05263, 0.0, 0.0],
      [0.85714, 0.0, 0.0, 0.0, 0.0, 0.0, 0.07143, 0.07143, 0.0, 0.0, 0.0, 0.0, 0.0, 0.0, 0.0, 0.0],
      [0.0, 0.28571, 0.42857, 0.14286, 0.0, 0.0, 0.0, 0.0, 0.0, 0.0, 0.07143, 0.07143, 0.0, 0.0, 0.0, 0.0],
      [0.0, 0.0, 0.0, 0.0, 0.5, 0.0, 0.0, 0.5, 0.0, 0.0, 0.0, 0.0, 0.0, 0.0, 0.0, 0.0],
      [0.0, 0.0, 0.0, 0.0, 0.5, 0.0, 0.5, 0.0, 0.0, 0.0, 0.0, 0.0, 0.0, 0.0, 0.0, 0.0],
      [0.5, 0.0, 0.0, 0.0, 0.0, 0.0, 0.0, 0.0, 0.0, 0.5, 0.0, 0.0, 0.0, 0.0, 0.0, 0.0],
      [0.5, 0.0, 0.0, 0.0, 0.0, 0.0, 0.0, 0.0, 0.5, 0.0, 0.0, 0.0, 0.0, 0.0, 0.0, 0.0],
      [0.0, 0.33333, 0.22222, 0.33333, 0.0, 0.11111, 0.0, 0.0, 0.0, 0.0, 0.0, 0.0, 0.0, 0.0, 0.0, 0.0],
      [0.0, 0.25, 0.5, 0.0, 0.0, 0.25, 0.0, 0.0, 0.0, 0.0, 0.0, 0.0, 0.0, 0.0, 0.0, 0.0],
      [1.0, 0.0, 0.0, 0.0, 0.0, 0.0, 0.0, 0.0, 0.0, 0.0, 0.0, 0.0, 0.0, 0.0, 0.0, 0.0],
      [0.0, 0.0, 0.5, 0.5, 0.0, 0.0, 0.0, 0.0, 0.0, 0.0, 0.0, 0.0, 0.0, 0.0, 0.0, 0.0],
      [1.0, 0.0, 0.0, 0.0, 0.0, 0.0, 0.0, 0.0, 0.0, 0.0, 0.0, 0.0, 0.0, 0.0, 0.0, 0.0],
      [0.0, 1.0, 0.0, 0.0, 0.0, 0.0, 0.0, 0.0, 0.0, 0.0, 0.0, 0.0, 0.0, 0.0, 0.0, 0.0]
    ]
  }],
  "first_interactions_between_characters": {
    "Ebenezer Scrooge": {
      "Jacob Marley": "There it stood, years afterwards, above the warehouse door: Scrooge and Marley.",
      "Valentine": "And Valentine,\" said Scrooge, \"and his wild brother, Orson; there they go!",
      "Orson": "And Valentine,\" said Scrooge, \"and his wild brother, Orson; there they go!",
      "Tiny Tim": "\"Spirit,\" said Scrooge with an interest he had never felt before, \"tell me if Tiny Tim will live.\"  ",
      "Fred": "\"More shame for him, Fred!\" said Scrooge's niece indignantly."
    },
    "Jacob Marley": {
      "Pharaoh": "There were Cains and Abels, Pharaoh's daughters, Queens of Sheba, Angelic messengers descending through the air on clouds like feather beds, Abrahams, Belshazzars, Apostles putting off to sea in butter-boats, hundreds of figures to attract his thoughts; and yet that face of Marley, seven years dead, came like the ancient Prophet's rod, and swallowed up the whole.",
      "Prophet": "There were Cains and Abels, Pharaoh's daughters, Queens of Sheba, Angelic messengers descending through the air on clouds like feather beds, Abrahams, Belshazzars, Apostles putting off to sea in butter-boats, hundreds of figures to attract his thoughts; and yet that face of Marley, seven years dead, came like the ancient Prophet's rod, and swallowed up the whole."
    },
    "Pharaoh": {
      "Prophet": "There were Cains and Abels, Pharaoh's daughters, Queens of Sheba, Angelic messengers descending through the air on clouds like feather beds, Abrahams, Belshazzars, Apostles putting off to sea in butter-boats, hundreds of figures to attract his thoughts; and yet that face of Marley, seven years dead, came like the ancient Prophet's rod, and swallowed up the whole."
    },
    "Orson": {
      "Valentine": "And Valentine,\" said Scrooge, \"and his wild brother, Orson; there they go!"
    },
    "Dick Wilkins": {
      "Ebenezer Scrooge": "\"Dick Wilkins, to be sure!\" said Scrooge to the Ghost."
    },
    "Bob Cratchit": {
      "Ebenezer Scrooge": "And perhaps it was the pleasure the good Spirit had in showing off this power of his, or else it was his own kind, generous, hearty nature, and his sympathy with all poor men, that led him straight to Scrooge's clerk's; for there he went, and took Scrooge with him, holding to his robe; and, on the threshold of the door, the Spirit smiled, and stopped to bless Bob Cratchit's dwelling with the sprinklings of his torch.",
      "Peter Cratchit": "Then up rose Mrs. Cratchit, Cratchit's wife, dressed out but poorly in a twice-turned gown, but brave in ribbons, which are cheap, and make a goodly show for sixpence; and she laid the cloth, assisted by Belinda Cratchit, second of her daughters, also brave in ribbons; while Master Peter Cratchit plunged a fork into the saucepan of potatoes, and, getting the corners of his monstrous shirt collar (Bob's private property, conferred upon his son and heir in honour of the day) into his mouth, rejoiced to find himself so gallantly attired, and yearned to show his linen in the fashionable Parks.",
      "Parks": "Then up rose Mrs. Cratchit, Cratchit's wife, dressed out but poorly in a twice-turned gown, but brave in ribbons, which are cheap, and make a goodly show for sixpence; and she laid the cloth, assisted by Belinda Cratchit, second of her daughters, also brave in ribbons; while Master Peter Cratchit plunged a fork into the saucepan of potatoes, and, getting the corners of his monstrous shirt collar (Bob's private property, conferred upon his son and heir in honour of the day) into his mouth, rejoiced to find himself so gallantly attired, and yearned to show his linen in the fashionable Parks.",
      "Martha": "So Martha hid herself, and in came little Bob, the father, with at least three feet of comforter, exclusive of the fringe, hanging down before him; and his threadbare clothes darned up and brushed to look seasonable; and Tiny Tim upon his shoulder.",
      "Tiny Tim": "So Martha hid herself, and in came little Bob, the father, with at least three feet of comforter, exclusive of the fringe, hanging down before him; and his threadbare clothes darned up and brushed to look seasonable; and Tiny Tim upon his shoulder.",
      "Joe Miller": "Joe Miller never made such a joke as sending it to Bob's will be!\"  "
    },
    "Belinda Cratchit": {
      "Peter Cratchit": "Then up rose Mrs. Cratchit, Cratchit's wife, dressed out but poorly in a twice-turned gown, but brave in ribbons, which are cheap, and make a goodly show for sixpence; and she laid the cloth, assisted by Belinda Cratchit, second of her daughters, also brave in ribbons; while Master Peter Cratchit plunged a fork into the saucepan of potatoes, and, getting the corners of his monstrous shirt collar (Bob's private property, conferred upon his son and heir in honour of the day) into his mouth, rejoiced to find himself so gallantly attired, and yearned to show his linen in the fashionable Parks.",
      "Bob Cratchit": "Then up rose Mrs. Cratchit, Cratchit's wife, dressed out but poorly in a twice-turned gown, but brave in ribbons, which are cheap, and make a goodly show for sixpence; and she laid the cloth, assisted by Belinda Cratchit, second of her daughters, also brave in ribbons; while Master Peter Cratchit plunged a fork into the saucepan of potatoes, and, getting the corners of his monstrous shirt collar (Bob's private property, conferred upon his son and heir in honour of the day) into his mouth, rejoiced to find himself so gallantly attired, and yearned to show his linen in the fashionable Parks.",
      "Parks": "Then up rose Mrs. Cratchit, Cratchit's wife, dressed out but poorly in a twice-turned gown, but brave in ribbons, which are cheap, and make a goodly show for sixpence; and she laid the cloth, assisted by Belinda Cratchit, second of her daughters, also brave in ribbons; while Master Peter Cratchit plunged a fork into the saucepan of potatoes, and, getting the corners of his monstrous shirt collar (Bob's private property, conferred upon his son and heir in honour of the day) into his mouth, rejoiced to find himself so gallantly attired, and yearned to show his linen in the fashionable Parks.",
      "Tiny Tim": "\"And how did little Tim behave?\" asked Mrs. Cratchit when she had rallied Bob on his credulity, and Bob had hugged his daughter to his heart's content.  ",
      "Martha": "Mrs. Cratchit made the gravy (ready beforehand in a little saucepan) hissing hot; Master Peter mashed the potatoes with incredible vigour; Miss Belinda sweetened up the apple sauce; Martha dusted the hot plates; Bob took Tiny Tim beside him in a tiny corner at the table; the two young Cratchits set chairs for everybody, not forgetting themselves, and, mounting guard upon their posts, crammed spoons into their mouths, lest they should shriek for goose before their turn came to be helped.",
      "Hurrah": "It was succeeded by a breathless pause, as Mrs. Cratchit, looking slowly all along the carving-knife, prepared to plunge it in the breast; but when she did, and when the long-expected gush of stuffing issued forth, one murmur of delight arose all round the board, and even Tiny Tim, excited by the two young Cratchits, beat on the table with the handle of his knife, and feebly cried Hurrah!  "
    },
    "Parks": {
      "Peter Cratchit": "Then up rose Mrs. Cratchit, Cratchit's wife, dressed out but poorly in a twice-turned gown, but brave in ribbons, which are cheap, and make a goodly show for sixpence; and she laid the cloth, assisted by Belinda Cratchit, second of her daughters, also brave in ribbons; while Master Peter Cratchit plunged a fork into the saucepan of potatoes, and, getting the corners of his monstrous shirt collar (Bob's private property, conferred upon his son and heir in honour of the day) into his mouth, rejoiced to find himself so gallantly attired, and yearned to show his linen in the fashionable Parks."
    },
    "Martha": {
      "Tiny Tim": "So Martha hid herself, and in came little Bob, the father, with at least three feet of comforter, exclusive of the fringe, hanging down before him; and his threadbare clothes darned up and brushed to look seasonable; and Tiny Tim upon his shoulder.",
      "Peter Cratchit": "Mrs. Cratchit made the gravy (ready beforehand in a little saucepan) hissing hot; Master Peter mashed the potatoes with incredible vigour; Miss Belinda sweetened up the apple sauce; Martha dusted the hot plates; Bob took Tiny Tim beside him in a tiny corner at the table; the two young Cratchits set chairs for everybody, not forgetting themselves, and, mounting guard upon their posts, crammed spoons into their mouths, lest they should shriek for goose before their turn came to be helped."
    },
    "Peter Cratchit": {
      "Tiny Tim": "His active little crutch was heard upon the floor, and back came Tiny Tim before another word was spoken, escorted by his brother and sister to his stool beside the fire; and while Bob, turning up his cuffs--as if, poor fellow, they were capable of being made more shabby--compounded some hot mixture in a jug with gin and lemons, and stirred it round and round, and put it on the hob to simmer, Master Peter and the two ubiquitous young Cratchits went to fetch the goose, with which they soon returned in high procession.  "
    },
    "Hurrah": {
      "Tiny Tim": "It was succeeded by a breathless pause, as Mrs. Cratchit, looking slowly all along the carving-knife, prepared to plunge it in the breast; but when she did, and when the long-expected gush of stuffing issued forth, one murmur of delight arose all round the board, and even Tiny Tim, excited by the two young Cratchits, beat on the table with the handle of his knife, and feebly cried Hurrah!  "
    }
  },
  "first_interactions_overall": {
    "Ebenezer Scrooge": {
      "with": "Jacob Marley",
      "context": "There it stood, years afterwards, above the warehouse door: Scrooge and Marley."
    },
    "Jacob Marley": {
      "with": "Ebenezer Scrooge",
      "context": "There it stood, years afterwards, above the warehouse door: Scrooge and Marley."
    },
    "Pharaoh": {
      "with": "Jacob Marley",
      "context": "There were Cains and Abels, Pharaoh's daughters, Queens of Sheba, Angelic messengers descending through the air on clouds like feather beds, Abrahams, Belshazzars, Apostles putting off to sea in butter-boats, hundreds of figures to attract his thoughts; and yet that face of Marley, seven years dead, came like the ancient Prophet's rod, and swallowed up the whole."
    },
    "Prophet": {
      "with": "Pharaoh",
      "context": "There were Cains and Abels, Pharaoh's daughters, Queens of Sheba, Angelic messengers descending through the air on clouds like feather beds, Abrahams, Belshazzars, Apostles putting off to sea in butter-boats, hundreds of figures to attract his thoughts; and yet that face of Marley, seven years dead, came like the ancient Prophet's rod, and swallowed up the whole."
    },
    "Valentine": {
      "with": "Ebenezer Scrooge",
      "context": "And Valentine,\" said Scrooge, \"and his wild brother, Orson; there they go!"
    },
    "Orson": {
      "with": "Valentine",
      "context": "And Valentine,\" said Scrooge, \"and his wild brother, Orson; there they go!"
    },
    "Dick Wilkins": {
      "with": "Ebenezer Scrooge",
      "context": "\"Dick Wilkins, to be sure!\" said Scrooge to the Ghost."
    },
    "Bob Cratchit": {
      "with": "Ebenezer Scrooge",
      "context": "And perhaps it was the pleasure the good Spirit had in showing off this power of his, or else it was his own kind, generous, hearty nature, and his sympathy with all poor men, that led him straight to Scrooge's clerk's; for there he went, and took Scrooge with him, holding to his robe; and, on the threshold of the door, the Spirit smiled, and stopped to bless Bob Cratchit's dwelling with the sprinklings of his torch."
    },
    "Belinda Cratchit": {
      "with": "Peter Cratchit",
      "context": "Then up rose Mrs. Cratchit, Cratchit's wife, dressed out but poorly in a twice-turned gown, but brave in ribbons, which are cheap, and make a goodly show for sixpence; and she laid the cloth, assisted by Belinda Cratchit, second of her daughters, also brave in ribbons; while Master Peter Cratchit plunged a fork into the saucepan of potatoes, and, getting the corners of his monstrous shirt collar (Bob's private property, conferred upon his son and heir in honour of the day) into his mouth, rejoiced to find himself so gallantly attired, and yearned to show his linen in the fashionable Parks."
    },
    "Peter Cratchit": {
      "with": "Belinda Cratchit",
      "context": "Then up rose Mrs. Cratchit, Cratchit's wife, dressed out but poorly in a twice-turned gown, but brave in ribbons, which are cheap, and make a goodly show for sixpence; and she laid the cloth, assisted by Belinda Cratchit, second of her daughters, also brave in ribbons; while Master Peter Cratchit plunged a fork into the saucepan of potatoes, and, getting the corners of his monstrous shirt collar (Bob's private property, conferred upon his son and heir in honour of the day) into his mouth, rejoiced to find himself so gallantly attired, and yearned to show his linen in the fashionable Parks."
    },
    "Parks": {
      "with": "Belinda Cratchit",
      "context": "Then up rose Mrs. Cratchit, Cratchit's wife, dressed out but poorly in a twice-turned gown, but brave in ribbons, which are cheap, and make a goodly show for sixpence; and she laid the cloth, assisted by Belinda Cratchit, second of her daughters, also brave in ribbons; while Master Peter Cratchit plunged a fork into the saucepan of potatoes, and, getting the corners of his monstrous shirt collar (Bob's private property, conferred upon his son and heir in honour of the day) into his mouth, rejoiced to find himself so gallantly attired, and yearned to show his linen in the fashionable Parks."
    },
    "Martha": {
      "with": "Bob Cratchit",
      "context": "So Martha hid herself, and in came little Bob, the father, with at least three feet of comforter, exclusive of the fringe, hanging down before him; and his threadbare clothes darned up and brushed to look seasonable; and Tiny Tim upon his shoulder."
    },
    "Tiny Tim": {
      "with": "Martha",
      "context": "So Martha hid herself, and in came little Bob, the father, with at least three feet of comforter, exclusive of the fringe, hanging down before him; and his threadbare clothes darned up and brushed to look seasonable; and Tiny Tim upon his shoulder."
    },
    "Hurrah": {
      "with": "Belinda Cratchit",
      "context": "It was succeeded by a breathless pause, as Mrs. Cratchit, looking slowly all along the carving-knife, prepared to plunge it in the breast; but when she did, and when the long-expected gush of stuffing issued forth, one murmur of delight arose all round the board, and even Tiny Tim, excited by the two young Cratchits, beat on the table with the handle of his knife, and feebly cried Hurrah!  "
    },
    "Fred": {
      "with": "Ebenezer Scrooge",
      "context": "\"More shame for him, Fred!\" said Scrooge's niece indignantly."
    },
    "Joe Miller": {
      "with": "Sha",
      "context": "\"I certainly shan't hold my hand, when I can get anything in it by reaching it out, for the sake of such a man as He was, I promise you, Joe,\" returned the woman coolly."
    }
  }
}